rentalgivediscount/__init__.py
product_discounts-1.0.0.dist-info/LICENSE.txt
product_discounts-1.0.0.dist-info/METADATA
product_discounts-1.0.0.dist-info/WHEEL
product_discounts-1.0.0.dist-info/top_level.txt
product_discounts-1.0.0.dist-info/RECORD
