Metadata-Version: 2.1
Name: product-discounts
Version: 1.0.0
Summary: A package for applying discounts to products
Home-page: https://github.com/your_username/product_discounts
Author: Musthaq
Author-email: musthaqmohammed757@gmail.com
Classifier: Development Status :: 5 - Production/Stable
Classifier: Intended Audience :: Developers
Classifier: License :: OSI Approved :: MIT License
Classifier: Programming Language :: Python :: 3
Classifier: Programming Language :: Python :: 3.6
Classifier: Programming Language :: Python :: 3.7
Classifier: Programming Language :: Python :: 3.8
Classifier: Programming Language :: Python :: 3.9
License-File: LICENSE.txt
